tinyutils/__init__.py
tinyutils/adb/__init__.py
tinyutils/adb/adb_utils.py
tinyutils/config/__init__.py
tinyutils/config/config_utils.py
tinyutils/csv/__init__.py
tinyutils/csv/csv_utils.py
tinyutils/echarts/__init__.py
tinyutils/echarts/echarts_utils.py
tinyutils/excel/__init__.py
tinyutils/excel/excel_utils.py
tinyutils/time/__init__.py
tinyutils/time/time_utils.py
tinyutils-0.0.9.dist-info/LICENSE.txt
tinyutils-0.0.9.dist-info/METADATA
tinyutils-0.0.9.dist-info/WHEEL
tinyutils-0.0.9.dist-info/top_level.txt
tinyutils-0.0.9.dist-info/RECORD
