Metadata-Version: 2.1
Name: tinyutils
Version: 0.0.9
Summary: A set of tiny utils
Home-page: https://github.com/fengzongming/tinyutils
Author: fengzongming
Author-email: dremeue@163.com
License: UNKNOWN
Keywords: tiny utils
Platform: UNKNOWN
Classifier: Development Status :: 3 - Alpha
Classifier: Intended Audience :: Developers
Classifier: Topic :: Software Development :: Build Tools
Classifier: License :: OSI Approved :: MIT License
Classifier: Programming Language :: Python :: 3.6
Classifier: Programming Language :: Python :: 3.7
Classifier: Programming Language :: Python :: 3.8
Classifier: Programming Language :: Python
Requires-Dist: openpyxl (>=3.0.3)
Requires-Dist: pyecharts (>=1.8.1)
